{
    "TEST": [
    {
      "name": "Senator Steve Chives",
      "email": "colonelreb@rocketmail.com"
    },
    {
      "name": "Senator Lovie Mary",
      "email": "test@ussenate.gov"
    }
  ],

  "AK": [
    {
      "name": "Lisa Murkowski (R)",
      "email": "lisa.murkowski@ussenate.gov"
    },
    {
      "name": "Dan Sullivan (R)",
      "email": "dan.sullivan@ussenate.gov"
    }
  ],
  "AL": [
    {
      "name": "Katie Britt (R)",
      "email": "katie.britt@ussenate.gov"
    },
    {
      "name": "Tommy Tuberville (R)",
      "email": "tommy.tuberville@ussenate.gov"
    }
  ],
  "AR": [
    {
      "name": "John Boozman (R)",
      "email": "john.boozman@ussenate.gov"
    },
    {
      "name": "Tom Cotton (R)",
      "email": "tom.cotton@ussenate.gov"
    }
  ],
  "AZ": [
    {
      "name": "Ruben Gallego (D)",
      "email": "ruben.gallego@ussenate.gov"
    },
    {
      "name": "Mark Kelly (D)",
      "email": "mark.kelly@ussenate.gov"
    }
  ],
  "CA": [
    {
      "name": "Alex Padilla (D)",
      "email": "alex.padilla@ussenate.gov"
    },
    {
      "name": "Adam Schiff (D)",
      "email": "adam.schiff@ussenate.gov"
    }
  ],
  "CO": [
    {
      "name": "Michael Bennet (D)",
      "email": "michael.bennet@ussenate.gov"
    },
    {
      "name": "John Hickenlooper (D)",
      "email": "john.hickenlooper@ussenate.gov"
    }
  ],
  "CT": [
    {
      "name": "Richard Blumenthal (D)",
      "email": "richard.blumenthal@ussenate.gov"
    },
    {
      "name": "Christopher Murphy (D)",
      "email": "christopher.murphy@ussenate.gov"
    }
  ],
  "DE": [
    {
      "name": "Lisa Blunt Rochester (D)",
      "email": "lisa.blunt@ussenate.gov"
    },
    {
      "name": "Christopher Coons (D)",
      "email": "christopher.coons@ussenate.gov"
    }
  ],
  "FL": [
    {
      "name": "Ashley Moody (R)",
      "email": "ashley.moody@ussenate.gov"
    },
    {
      "name": "Rick Scott (R)",
      "email": "rick.scott@ussenate.gov"
    }
  ],
  "GA": [
    {
      "name": "Jon Ossoff (D)",
      "email": "jon.ossoff@ussenate.gov"
    },
    {
      "name": "Raphael Warnock (D)",
      "email": "raphael.warnock@ussenate.gov"
    }
  ],
  "HI": [
    {
      "name": "Mazie Hirono (D)",
      "email": "mazie.hirono@ussenate.gov"
    },
    {
      "name": "Brian Schatz (D)",
      "email": "brian.schatz@ussenate.gov"
    }
  ],
  "IA": [
    {
      "name": "Joni Ernst (R)",
      "email": "joni.ernst@ussenate.gov"
    },
    {
      "name": "Chuck Grassley (R)",
      "email": "chuck.grassley@ussenate.gov"
    }
  ],
  "ID": [
    {
      "name": "Mike Crapo (R)",
      "email": "mike.crapo@ussenate.gov"
    },
    {
      "name": "James Risch (R)",
      "email": "james.risch@ussenate.gov"
    }
  ],
  "IL": [
    {
      "name": "Tammy Duckworth (D)",
      "email": "tammy.duckworth@ussenate.gov"
    },
    {
      "name": "Richard Durbin (D)",
      "email": "richard.durbin@ussenate.gov"
    }
  ],
  "IN": [
    {
      "name": "Jim Banks (R)",
      "email": "jim.banks@ussenate.gov"
    },
    {
      "name": "Todd Young (R)",
      "email": "todd.young@ussenate.gov"
    }
  ],
  "KS": [
    {
      "name": "Roger Marshall (R)",
      "email": "roger.marshall@ussenate.gov"
    },
    {
      "name": "Jerry Moran (R)",
      "email": "jerry.moran@ussenate.gov"
    }
  ],
  "KY": [
    {
      "name": "Mitch McConnell (R)",
      "email": "mitch.mcconnell@ussenate.gov"
    },
    {
      "name": "Rand Paul (R)",
      "email": "rand.paul@ussenate.gov"
    }
  ],
  "LA": [
    {
      "name": "Bill Cassidy (R)",
      "email": "bill.cassidy@ussenate.gov"
    },
    {
      "name": "John Kennedy (R)",
      "email": "john.kennedy@ussenate.gov"
    }
  ],
  "MA": [
    {
      "name": "Edward Markey (D)",
      "email": "edward.markey@ussenate.gov"
    },
    {
      "name": "Elizabeth Warren (D)",
      "email": "elizabeth.warren@ussenate.gov"
    }
  ],
  "MD": [
    {
      "name": "Angela Alsobrooks (D)",
      "email": "angela.alsobrooks@ussenate.gov"
    },
    {
      "name": "Chris Van Hollen (D)",
      "email": "chris.van@ussenate.gov"
    }
  ],
  "ME": [
    {
      "name": "Susan Collins (R)",
      "email": "susan.collins@ussenate.gov"
    },
    {
      "name": "Angus King (I)",
      "email": "angus.king@ussenate.gov"
    }
  ],
  "MI": [
    {
      "name": "Gary Peters (D)",
      "email": "gary.peters@ussenate.gov"
    },
    {
      "name": "Elissa Slotkin (D)",
      "email": "elissa.slotkin@ussenate.gov"
    }
  ],
  "MN": [
    {
      "name": "Amy Klobuchar (D)",
      "email": "amy.klobuchar@ussenate.gov"
    },
    {
      "name": "Tina Smith (D)",
      "email": "tina.smith@ussenate.gov"
    }
  ],
  "MO": [
    {
      "name": "Josh Hawley (R)",
      "email": "josh.hawley@ussenate.gov"
    },
    {
      "name": "Eric Schmitt (R)",
      "email": "eric.schmitt@ussenate.gov"
    }
  ],
  "MS": [
    {
      "name": "Cindy Hyde-Smith (R)",
      "email": "cindy.hyde-smith@ussenate.gov"
    },
    {
      "name": "Roger Wicker (R)",
      "email": "roger.wicker@ussenate.gov"
    }
  ],
  "MT": [
    {
      "name": "Steve Daines (R)",
      "email": "steve.daines@ussenate.gov"
    },
    {
      "name": "Tim Sheehy (R)",
      "email": "tim.sheehy@ussenate.gov"
    }
  ],
  "NC": [
    {
      "name": "Ted Budd (R)",
      "email": "ted.budd@ussenate.gov"
    },
    {
      "name": "Thomas Tillis (R)",
      "email": "thomas.tillis@ussenate.gov"
    }
  ],
  "ND": [
    {
      "name": "Kevin Cramer (R)",
      "email": "kevin.cramer@ussenate.gov"
    },
    {
      "name": "John Hoeven (R)",
      "email": "john.hoeven@ussenate.gov"
    }
  ],
  "NE": [
    {
      "name": "Deb Fischer (R)",
      "email": "deb.fischer@ussenate.gov"
    },
    {
      "name": "Pete Ricketts (R)",
      "email": "pete.ricketts@ussenate.gov"
    }
  ],
  "NH": [
    {
      "name": "Maggie Hassan (D)",
      "email": "maggie.hassan@ussenate.gov"
    },
    {
      "name": "Jeanne Shaheen (D)",
      "email": "jeanne.shaheen@ussenate.gov"
    }
  ],
  "NJ": [
    {
      "name": "Cory Booker (D)",
      "email": "cory.booker@ussenate.gov"
    },
    {
      "name": "Andy Kim (D)",
      "email": "andy.kim@ussenate.gov"
    }
  ],
  "NM": [
    {
      "name": "Martin Heinrich (D)",
      "email": "martin.heinrich@ussenate.gov"
    },
    {
      "name": "Ben Lujan (D)",
      "email": "ben.lujan@ussenate.gov"
    }
  ],
  "NV": [
    {
      "name": "Catherine Cortez Masto (D)",
      "email": "catherine.cortez@ussenate.gov"
    },
    {
      "name": "Jacky Rosen (D)",
      "email": "jacky.rosen@ussenate.gov"
    }
  ],
  "NY": [
    {
      "name": "Kirsten Gillibrand (D)",
      "email": "kirsten.gillibrand@ussenate.gov"
    },
    {
      "name": "Charles Schumer (D)",
      "email": "charles.schumer@ussenate.gov"
    }
  ],
  "OH": [
    {
      "name": "Jon Husted (R)",
      "email": "jon.husted@ussenate.gov"
    },
    {
      "name": "Bernie Moreno (R)",
      "email": "bernie.moreno@ussenate.gov"
    }
  ],
  "OK": [
    {
      "name": "James Lankford (R)",
      "email": "james.lankford@ussenate.gov"
    },
    {
      "name": "Markwayne Mullin (R)",
      "email": "markwayne.mullin@ussenate.gov"
    }
  ],
  "OR": [
    {
      "name": "Jeff Merkley (D)",
      "email": "jeff.merkley@ussenate.gov"
    },
    {
      "name": "Ron Wyden (D)",
      "email": "ron.wyden@ussenate.gov"
    }
  ],
  "PA": [
    {
      "name": "John Fetterman (D)",
      "email": "john.fetterman@ussenate.gov"
    },
    {
      "name": "David McCormick (R)",
      "email": "david.mccormick@ussenate.gov"
    }
  ],
  "RI": [
    {
      "name": "John Reed (D)",
      "email": "john.reed@ussenate.gov"
    },
    {
      "name": "Sheldon Whitehouse (D)",
      "email": "sheldon.whitehouse@ussenate.gov"
    }
  ],
  "SC": [
    {
      "name": "Lindsey Graham (R)",
      "email": "lindsey.graham@ussenate.gov"
    },
    {
      "name": "Tim Scott (R)",
      "email": "tim.scott@ussenate.gov"
    }
  ],
  "SD": [
    {
      "name": "Mike Rounds (R)",
      "email": "mike.rounds@ussenate.gov"
    },
    {
      "name": "John Thune (R)",
      "email": "john.thune@ussenate.gov"
    }
  ],
  "TN": [
    {
      "name": "Marsha Blackburn (R)",
      "email": "marsha.blackburn@ussenate.gov"
    },
    {
      "name": "Bill Hagerty (R)",
      "email": "bill.hagerty@ussenate.gov"
    }
  ],
  "TX": [
    {
      "name": "John Cornyn (R)",
      "email": "john.cornyn@ussenate.gov"
    },
    {
      "name": "Ted Cruz (R)",
      "email": "ted.cruz@ussenate.gov"
    }
  ],
  "UT": [
    {
      "name": "John Curtis (R)",
      "email": "john.curtis@ussenate.gov"
    },
    {
      "name": "Mike Lee (R)",
      "email": "mike.lee@ussenate.gov"
    }
  ],
  "VA": [
    {
      "name": "Timothy Kaine (D)",
      "email": "timothy.kaine@ussenate.gov"
    },
    {
      "name": "Mark Warner (D)",
      "email": "mark.warner@ussenate.gov"
    }
  ],
  "VT": [
    {
      "name": "Bernie Sanders (I)",
      "email": "bernie.sanders@ussenate.gov"
    },
    {
      "name": "Peter Welch (D)",
      "email": "peter.welch@ussenate.gov"
    }
  ],
  "WA": [
    {
      "name": "Maria Cantwell (D)",
      "email": "maria.cantwell@ussenate.gov"
    },
    {
      "name": "Patty Murray (D)",
      "email": "patty.murray@ussenate.gov"
    }
  ],
  "WI": [
    {
      "name": "Tammy Baldwin (D)",
      "email": "tammy.baldwin@ussenate.gov"
    },
    {
      "name": "Ron Johnson (R)",
      "email": "ron.johnson@ussenate.gov"
    }
  ],
  "WV": [
    {
      "name": "Shelley Capito (R)",
      "email": "shelley.capito@ussenate.gov"
    },
    {
      "name": "James Justice (R)",
      "email": "james.justice@ussenate.gov"
    }
  ],
  "WY": [
    {
      "name": "John Barrasso (R)",
      "email": "john.barrasso@ussenate.gov"
    },
    {
      "name": "Cynthia Lummis (R)",
      "email": "cynthia.lummis@ussenate.gov"
    }
  ]
}
